Workbook

Sheet Summary
A1: COPART, INC. (NASDAQ: CPRT) - LONG | HFAC x Citadel 2026 Stock Pitch | Valuation model summary
A3: Recommendation | B3: LONG
A4: Current price (24-Sep-2026) | B4: =Inputs!$B$6
A5: 12-month probability-weighted target | B5: =Valuation!$B$32
A6: Expected return | B6: =Valuation!$B$33
A7: Bear / Base / Bull target | B7: =TEXT(Valuation!B25,"$0.00")&" / "&TEXT(Valuation!C25,"$0.00")&" / "&TEXT(Valuation!D25,"$0.00")
A8: Bear / Base / Bull return | B8: =TEXT(Valuation!B26,"0%")&" / "&TEXT(Valuation!C26,"0%")&" / "&TEXT(Valuation!D26,"0%")
A9: Probabilities (Bear/Base/Bull) | B9: =TEXT(Inputs!B21,"0%")&" / "&TEXT(Inputs!C21,"0%")&" / "&TEXT(Inputs!D21,"0%")
A10: Market cap ($M) | B10: =Inputs!$B$12
A11: Enterprise value ($M) | B11: =Inputs!$B$13
A12: Current NTM P/E (consensus FY27E $1.63) | B12: =Inputs!$B$6/1.63
A13: Current EV / FY26A EBITDA | B13: =Inputs!$B$13/1882
A14: DCF value per share (active scenario) | B14: =DCF!B21
A15: Active scenario | B15: =Inputs!C17
A17: Sheet guide
A18: Inputs - all assumptions (blue), scenario selector (B17), probabilities, ACV deal terms, DCF inputs
A19: Historical - FY21-FY26 financials (Capital IQ export) and CapIQ multiple history
A20: Model - 5-year operating model for the ACTIVE scenario incl. ACV consolidation, buybacks, cash
A21: Scenarios - Bear / Base / Bull models side by side (feeds Valuation)
A22: Valuation - 12-month target price via P/E & EV/EBITDA per scenario, probability-weighted, P/E x EPS sensitivity
A23: DCF - 5-yr DCF on active scenario, WACC x g sensitivity
A24: Comps - RBA / KAR / CPRT history and implied values
A25: ACV Deal - deal multiples, synergy breakeven, EPS accretion/dilution sensitivity
A26: Sources: Copart FY26 press release & 10-K, Capital IQ export (provided), ACV/Copart merger press release (10-Sep-2026), Undiscovered Compounders deep dives (provided), public quotes 24-Sep-2026.

Sheet Inputs
A1: COPART (CPRT) - MODEL INPUTS | blue = hard-coded input, black = formula, green = link
A2: All $ in millions except per share. Fiscal year ends July 31.
A4: Market data & capitalization
A5: Valuation date | B5: 2026-09-25 | H5: Memo date
A6: Share price ($) | B6: 28.04 | H6: NASDAQ close 24-Sep-2026
A7: Basic shares outstanding (M) | B7: 925.811 | H7: CapIQ, latest (post FY26 buybacks)
A8: FY26 diluted weighted shares (M) | B8: 956.86 | H8: FY26 10-K / CapIQ
A9: Cash & HTM/short-term investments | B9: 4489.8 | H9: Balance sheet 31-Jul-2026
A10: Total debt (leases; no funded debt) | B10: 88.4 | H10: Balance sheet 31-Jul-2026
A11: Minority interest | B11: 16.6 | H11: Balance sheet 31-Jul-2026
A12: Market capitalization | B12: =B6*B7 | H12: formula
A13: Enterprise value | B13: =B12-B9+B10+B11 | H13: formula
A14: Target horizon (months) | B14: 12 | H14: Competition: 3-12 month horizon
A16: Scenario selector (drives 'Model' and 'DCF' sheets)
A17: Active scenario (1 = Bear, 2 = Base, 3 = Bull) | B17: 2 | C17: =CHOOSE(B17,"Bear","Base","Bull")
A19: Operating assumptions by scenario
B20: Bear | C20: Base | D20: Bull | H20: Rationale / source
A21: Scenario probability | B21: 0.25 | C21: 0.5 | D21: 0.25 | E21: =SUM(B21:D21) | H21: Must sum to 100%; base weighted to reflect Q4-26 assignment data
A22: US unit growth | B22: FY27E | C22: FY28E | D22: FY29E | E22: FY30E | F22: FY31E | H22: Q4-26 US insurance assignments +2.3% ex-one lost customer (Progressive); Q1-27 still down MSD, growth returns by Q4-27 (base)
A23: Bear | B23: -0.03 | C23: -0.01 | D23: 0 | E23: 0 | F23: 0
A24: Base | B24: -0.01 | C24: 0.03 | D24: 0.025 | E24: 0.025 | F24: 0.025
A25: Bull | B25: 0.01 | C25: 0.045 | D25: 0.04 | E25: 0.04 | F25: 0.04
A26: Active (per selector) | B26: =CHOOSE(Inputs!$B$17,B23,B24,B25) | C26: =CHOOSE(Inputs!$B$17,C23,C24,C25) | D26: =CHOOSE(Inputs!$B$17,D23,D24,D25) | E26: =CHOOSE(Inputs!$B$17,E23,E24,E25) | F26: =CHOOSE(Inputs!$B$17,F23,F24,F25)
A28: International unit growth | B28: FY27E | C28: FY28E | D28: FY29E | E28: FY30E | F28: FY31E | H28: Q4-26 intl units +10%, intl insurance +11.2%; FY26 intl revenue +8.5%; ex-FX mid/high-single digits
A29: Bear | B29: 0.025 | C29: 0.025 | D29: 0.025 | E29: 0.025 | F29: 0.025
A30: Base | B30: 0.055 | C30: 0.055 | D30: 0.055 | E30: 0.055 | F30: 0.055
A31: Bull | B31: 0.08 | C31: 0.08 | D31: 0.08 | E31: 0.08 | F31: 0.08
A32: Active (per selector) | B32: =CHOOSE(Inputs!$B$17,B29,B30,B31) | C32: =CHOOSE(Inputs!$B$17,C29,C30,C31) | D32: =CHOOSE(Inputs!$B$17,D29,D30,D31) | E32: =CHOOSE(Inputs!$B$17,E29,E30,E31) | F32: =CHOOSE(Inputs!$B$17,F29,F30,F31)
A34: Revenue per unit (RPU) growth | B34: FY27E | C34: FY28E | D34: FY29E | E34: FY30E | F34: FY31E | H34: FY26 RPU +5.7%; rising ASP & total-loss frequency (23.3% record CQ2-26), Title Express/long-haul fees. Bear = used-car deflation
A35: Bear | B35: 0.01 | C35: -0.01 | D35: -0.01 | E35: 0 | F35: 0
A36: Base | B36: 0.035 | C36: 0.035 | D36: 0.035 | E36: 0.035 | F36: 0.035
A37: Bull | B37: 0.055 | C37: 0.055 | D37: 0.05 | E37: 0.05 | F37: 0.05
A38: Active (per selector) | B38: =CHOOSE(Inputs!$B$17,B35,B36,B37) | C38: =CHOOSE(Inputs!$B$17,C35,C36,C37) | D38: =CHOOSE(Inputs!$B$17,D35,D36,D37) | E38: =CHOOSE(Inputs!$B$17,E35,E36,E37) | F38: =CHOOSE(Inputs!$B$17,F35,F36,F37)
A40: Core EBIT margin (ex-ACV) | B40: FY27E | C40: FY28E | D40: FY29E | E40: FY30E | F40: FY31E | H40: FY26 35.4% (FY25 37.7%). Operating leverage on fixed land base reverses when units grow; ~1pt of unit growth = ~$31M EBIT (deep dive)
A41: Bear | B41: 0.335 | C41: 0.325 | D41: 0.32 | E41: 0.32 | F41: 0.32
A42: Base | B42: 0.35 | C42: 0.36 | D42: 0.365 | E42: 0.37 | F42: 0.37
A43: Bull | B43: 0.36 | C43: 0.375 | D43: 0.385 | E43: 0.39 | F43: 0.39
A44: Active (per selector) | B44: =CHOOSE(Inputs!$B$17,B41,B42,B43) | C44: =CHOOSE(Inputs!$B$17,C41,C42,C43) | D44: =CHOOSE(Inputs!$B$17,D41,D42,D43) | E44: =CHOOSE(Inputs!$B$17,E41,E42,E43) | F44: =CHOOSE(Inputs!$B$17,F41,F42,F43)
A46: D&A % revenue (ex-ACV) | B46: FY27E | C46: FY28E | D46: FY29E | E46: FY30E | F46: FY31E | H46: FY26 $229M = 4.9% of revenue
A47: Bear | B47: 0.05 | C47: 0.05 | D47: 0.05 | E47: 0.05 | F47: 0.05
A48: Base | B48: 0.05 | C48: 0.05 | D48: 0.05 | E48: 0.05 | F48: 0.05
A49: Bull | B49: 0.05 | C49: 0.05 | D49: 0.05 | E49: 0.05 | F49: 0.05
A50: Active (per selector) | B50: =CHOOSE(Inputs!$B$17,B47,B48,B49) | C50: =CHOOSE(Inputs!$B$17,C47,C48,C49) | D50: =CHOOSE(Inputs!$B$17,D47,D48,D49) | E50: =CHOOSE(Inputs!$B$17,E47,E48,E49) | F50: =CHOOSE(Inputs!$B$17,F47,F48,F49)
A52: Capex % revenue (ex-ACV) | B52: FY27E | C52: FY28E | D52: FY29E | E52: FY30E | F52: FY31E | H52: FY26 7.2% (land buying paused); FY24-25 ~12% incl. land banking; maintenance ~$230M (~5%)
A53: Bear | B53: 0.08 | C53: 0.08 | D53: 0.08 | E53: 0.08 | F53: 0.08
A54: Base | B54: 0.085 | C54: 0.085 | D54: 0.085 | E54: 0.085 | F54: 0.085
A55: Bull | B55: 0.095 | C55: 0.095 | D55: 0.095 | E55: 0.095 | F55: 0.095
A56: Active (per selector) | B56: =CHOOSE(Inputs!$B$17,B53,B54,B55) | C56: =CHOOSE(Inputs!$B$17,C53,C54,C55) | D56: =CHOOSE(Inputs!$B$17,D53,D54,D55) | E56: =CHOOSE(Inputs!$B$17,E53,E54,E55) | F56: =CHOOSE(Inputs!$B$17,F53,F54,F55)
A58: Change in NWC (% of revenue change) | B58: FY27E | C58: FY28E | D58: FY29E | E58: FY30E | F58: FY31E | H58: Historical NWC ~1% of OCF
A59: Bear | B59: 0.03 | C59: 0.03 | D59: 0.03 | E59: 0.03 | F59: 0.03
A60: Base | B60: 0.03 | C60: 0.03 | D60: 0.03 | E60: 0.03 | F60: 0.03
A61: Bull | B61: 0.03 | C61: 0.03 | D61: 0.03 | E61: 0.03 | F61: 0.03
A62: Active (per selector) | B62: =CHOOSE(Inputs!$B$17,B59,B60,B61) | C62: =CHOOSE(Inputs!$B$17,C59,C60,C61) | D62: =CHOOSE(Inputs!$B$17,D59,D60,D61) | E62: =CHOOSE(Inputs!$B$17,E59,E60,E61) | F62: =CHOOSE(Inputs!$B$17,F59,F60,F61)
A64: Effective tax rate | B64: FY27E | C64: FY28E | D64: FY29E | E64: FY30E | F64: FY31E | H64: FY26 19.3%, FY25 18.3%
A65: Bear | B65: 0.195 | C65: 0.195 | D65: 0.195 | E65: 0.195 | F65: 0.195
A66: Base | B66: 0.195 | C66: 0.195 | D66: 0.195 | E66: 0.195 | F66: 0.195
A67: Bull | B67: 0.195 | C67: 0.195 | D67: 0.195 | E67: 0.195 | F67: 0.195
A68: Active (per selector) | B68: =CHOOSE(Inputs!$B$17,B65,B66,B67) | C68: =CHOOSE(Inputs!$B$17,C65,C66,C67) | D68: =CHOOSE(Inputs!$B$17,D65,D66,D67) | E68: =CHOOSE(Inputs!$B$17,E65,E66,E67) | F68: =CHOOSE(Inputs!$B$17,F65,F66,F67)
A70: Yield on cash | B70: FY27E | C70: FY28E | D70: FY29E | E70: FY30E | F70: FY31E | H70: FY26 interest income $182M on ~$4.6B avg cash = 3.9%
A71: Bear | B71: 0.035 | C71: 0.035 | D71: 0.035 | E71: 0.035 | F71: 0.035
A72: Base | B72: 0.038 | C72: 0.038 | D72: 0.038 | E72: 0.038 | F72: 0.038
A73: Bull | B73: 0.038 | C73: 0.038 | D73: 0.038 | E73: 0.038 | F73: 0.038
A74: Active (per selector) | B74: =CHOOSE(Inputs!$B$17,B71,B72,B73) | C74: =CHOOSE(Inputs!$B$17,C71,C72,C73) | D74: =CHOOSE(Inputs!$B$17,D71,D72,D73) | E74: =CHOOSE(Inputs!$B$17,E71,E72,E73) | F74: =CHOOSE(Inputs!$B$17,F71,F72,F73)
A76: Share buybacks ($M / yr) | B76: FY27E | C76: FY28E | D76: FY29E | E76: FY30E | F76: FY31E | H76: FY26 $1.63B; paused for ACV; ~$2.6B cash left post-deal + $1.25B revolver
A77: Bear | B77: 200 | C77: 200 | D77: 300 | E77: 300 | F77: 300
A78: Base | B78: 500 | C78: 700 | D78: 800 | E78: 800 | F78: 800
A79: Bull | B79: 800 | C79: 1000 | D79: 1000 | E79: 1000 | F79: 1000
A80: Active (per selector) | B80: =CHOOSE(Inputs!$B$17,B77,B78,B79) | C80: =CHOOSE(Inputs!$B$17,C77,C78,C79) | D80: =CHOOSE(Inputs!$B$17,D77,D78,D79) | E80: =CHOOSE(Inputs!$B$17,E77,E78,E79) | F80: =CHOOSE(Inputs!$B$17,F77,F78,F79)
A82: Assumed avg buyback price ($) | B82: FY27E | C82: FY28E | D82: FY29E | E82: FY30E | F82: FY31E | H82: Assumption consistent with each scenario's price path
A83: Bear | B83: 26 | C83: 24 | D83: 24 | E83: 26 | F83: 28
A84: Base | B84: 30 | C84: 36 | D84: 40 | E84: 44 | F84: 48
A85: Bull | B85: 32 | C85: 42 | D85: 50 | E85: 56 | F85: 62
A86: Active (per selector) | B86: =CHOOSE(Inputs!$B$17,B83,B84,B85) | C86: =CHOOSE(Inputs!$B$17,C83,C84,C85) | D86: =CHOOSE(Inputs!$B$17,D83,D84,D85) | E86: =CHOOSE(Inputs!$B$17,E83,E84,E85) | F86: =CHOOSE(Inputs!$B$17,F83,F84,F85)
A88: Gross share issuance (SBC dilution) | B88: FY27E | C88: FY28E | D88: FY29E | E88: FY30E | F88: FY31E | H88: FY26 ~$31M issuance / SBC $39M
A89: Bear | B89: 0.003 | C89: 0.003 | D89: 0.003 | E89: 0.003 | F89: 0.003
A90: Base | B90: 0.003 | C90: 0.003 | D90: 0.003 | E90: 0.003 | F90: 0.003
A91: Bull | B91: 0.003 | C91: 0.003 | D91: 0.003 | E91: 0.003 | F91: 0.003
A92: Active (per selector) | B92: =CHOOSE(Inputs!$B$17,B89,B90,B91) | C92: =CHOOSE(Inputs!$B$17,C89,C90,C91) | D92: =CHOOSE(Inputs!$B$17,D89,D90,D91) | E92: =CHOOSE(Inputs!$B$17,E89,E90,E91) | F92: =CHOOSE(Inputs!$B$17,F89,F90,F91)
A94: ACV pretax synergies ($M) | B94: FY27E | C94: FY28E | D94: FY29E | E94: FY30E | F94: FY31E | H94: ACV deep dive: ~$25M needed for FY28 accretion; levers = yard sharing, logistics, buyer cross-sell, floorplan, G&A
A95: Bear | B95: 0 | C95: 0 | D95: 10 | E95: 20 | F95: 25
A96: Base | B96: 0 | C96: 25 | D96: 60 | E96: 90 | F96: 110
A97: Bull | B97: 0 | C97: 50 | D97: 110 | E97: 160 | F97: 190
A98: Active (per selector) | B98: =CHOOSE(Inputs!$B$17,B95,B96,B97) | C98: =CHOOSE(Inputs!$B$17,C95,C96,C97) | D98: =CHOOSE(Inputs!$B$17,D95,D96,D97) | E98: =CHOOSE(Inputs!$B$17,E95,E96,E97) | F98: =CHOOSE(Inputs!$B$17,F95,F96,F97)
A100: ACV revenue growth (CY) | B100: FY27E | C100: FY28E | D100: FY29E | E100: FY30E | F100: FY31E | H100: ACV CY25 $760M -> CY26 guide ~$850M (+12%)
A101: Bear | B101: 0.06 | C101: 0.06 | D101: 0.06 | E101: 0.06 | F101: 0.06
A102: Base | B102: 0.12 | C102: 0.11 | D102: 0.1 | E102: 0.09 | F102: 0.08
A103: Bull | B103: 0.15 | C103: 0.14 | D103: 0.12 | E103: 0.11 | F103: 0.1
A104: Active (per selector) | B104: =CHOOSE(Inputs!$B$17,B101,B102,B103) | C104: =CHOOSE(Inputs!$B$17,C101,C102,C103) | D104: =CHOOSE(Inputs!$B$17,D101,D102,D103) | E104: =CHOOSE(Inputs!$B$17,E101,E102,E103) | F104: =CHOOSE(Inputs!$B$17,F101,F102,F103)
A106: ACV adj. EBITDA margin (standalone) | B106: FY27E | C106: FY28E | D106: FY29E | E106: FY30E | F106: FY31E | H106: CY26 guide $73-77M on $850M = 8.8%
A107: Bear | B107: 0.085 | C107: 0.09 | D107: 0.095 | E107: 0.1 | F107: 0.1
A108: Base | B108: 0.1 | C108: 0.12 | D108: 0.14 | E108: 0.15 | F108: 0.16
A109: Bull | B109: 0.11 | C109: 0.14 | D109: 0.16 | E109: 0.18 | F109: 0.19
A110: Active (per selector) | B110: =CHOOSE(Inputs!$B$17,B107,B108,B109) | C110: =CHOOSE(Inputs!$B$17,C107,C108,C109) | D110: =CHOOSE(Inputs!$B$17,D107,D108,D109) | E110: =CHOOSE(Inputs!$B$17,E107,E108,E109) | F110: =CHOOSE(Inputs!$B$17,F107,F108,F109)
A112: Target P/E on NTM EPS (12-mo) | B112: 15 | C112: 24 | D112: 30 | E112: =CHOOSE(Inputs!$B$17,B112,C112,D112) | F112: <- active | H112: Now 17.7x NTM (CapIQ); 2-yr avg 27x; 5-10 yr avg ~30x+. Bear = de-rate to RBA/KAR level
A113: Target EV/EBITDA on NTM EBITDA (12-mo) | B113: 10 | C113: 15.5 | D113: 19 | E113: =CHOOSE(Inputs!$B$17,B113,C113,D113) | F113: <- active | H113: Now 11.3x NTM; 2-yr avg 18.9x; RBA ~13-15x LTM (levered, 30% lower margin)
A115: ACV Auctions acquisition (announced 10-Sep-2026)
A116: Equity purchase price ($M, cash) | B116: 1900 | H116: $10.50/sh tender; ~35x CY25 adj. EBITDA, 2.7x sales
A117: Expected close (fiscal month of FY27, 1-12) | B117: 5 | H117: Close targeted by CY-end 2026 -> ~Dec-2026 = month 5 of FY27
A118: Months consolidated in FY27 | B118: =12-B117 | H118: formula
A119: ACV CY2026E revenue ($M) | B119: 850 | H119: ACV guidance
...

Sheet Historical
A1: HISTORICAL FINANCIALS (S&P Capital IQ export; FY ends Jul-31; $M)
B3: FY21A | C3: FY22A | D3: FY23A | E3: FY24A | F3: FY25A | G3: FY26A
A4: Total revenue | B4: 2692.5 | C4: 3500.9 | D4: 3869.5 | E4: 4236.8 | F4: 4647 | G4: 4666.2
A5: US revenue | B5: 2272.1 | C5: 2945.2 | D5: 3189.6 | E5: 3464.7 | F5: 3855.1 | G5: 3807.4
A6: International revenue | B6: 420.4 | C6: 555.8 | D6: 679.9 | E6: 772.1 | F6: 791.9 | G6: 858.8
A7: Service revenue | F7: 3968.7 | G7: 3969.5
A8: Vehicle sales | F8: 678.3 | G8: 696.7
A9: Gross profit (co. definition) | B9: 1343.1 | C9: 1606.2 | D9: 1737 | E9: 1939.2 | F9: 2099.6 | G9: 2083.9
A10: Operating income (EBIT) | B10: 1136.4 | C10: 1375 | D10: 1486.6 | E10: 1573.2 | F10: 1752.7 | G10: 1652.6
A11: US EBIT | B11: 1023.6 | C11: 1247.6 | D11: 1368.1 | E11: 1428 | F11: 1480.9 | G11: 1419
A12: International EBIT | B12: 112.9 | C12: 127.4 | D12: 118.5 | E12: 144 | F12: 215.8 | G12: 233.6
A13: D&A | B13: 112.4 | C13: 128.8 | D13: 152.3 | E13: 181.1 | F13: 202.8 | G13: 229.4
A14: EBITDA | B14: 1248.8 | C14: 1503.8 | D14: 1638.9 | E14: 1754.3 | F14: 1955.5 | G14: 1882
A15: Interest & investment income (net) | B15: -20.2 | C15: -16.7 | D15: 65.9 | E15: 145.7 | F15: 178.9 | G15: 181.9
A16: Pre-tax income | B16: 1121.8 | C16: 1341 | D16: 1554.3 | E16: 1714.6 | F16: 1895.6 | G16: 1835
A17: Income tax | B17: 185.4 | C17: 250.8 | D17: 316.6 | E17: 352.3 | F17: 347.2 | G17: 354.6
A18: Net income | B18: 936.5 | C18: 1090.1 | D18: 1237.7 | E18: 1363 | F18: 1552.4 | G18: 1484.3
A19: Diluted EPS ($) | B19: 0.97 | C19: 1.13 | D19: 1.28 | E19: 1.4 | F19: 1.59 | G19: 1.55
A20: Diluted shares (M) | B20: 961.2 | C20: 964.6 | D20: 966.6 | E20: 974.8 | F20: 977.6 | G20: 956.9
... A25: Total debt (leases) | B25: 518.1 | C25: 119.5 | D25: 120.5 | E25: 118.7 | F25: 103.7 | G25: 88.4
A26: Land (at cost) | B26: 1428.3 | C26: 1526.4 | D26: 1812 | E26: 2027.6 | F26: 2394.6
A28: Derived ratios
A29: Revenue growth | C29: =IF(B4="","",C4/B4-1) | D29: =IF(C4="","",D4/C4-1) | E29: =IF(D4="","",E4/D4-1) | F29: =IF(E4="","",F4/E4-1) | G29: =IF(F4="","",G4/F4-1)
A30: EBIT margin | B30: =B10/B4 | C30: =C10/C4 | D30: =D10/D4 | E30: =E10/E4 | F30: =F10/F4 | G30: =G10/G4
A31: EBITDA margin | B31: =B14/B4 | C31: =C14/C4 | D31: =D14/D4 | E31: =E14/E4 | F31: =F14/F4 | G31: =G14/G4
A32: Free cash flow (CFO - capex) | B32: =B21+B22 | C32: =C21+C22 | D32: =D21+D22 | E32: =E21+E22 | F32: =F21+F22 | G32: =G21+G22
A33: FCF margin | B33: =(B21+B22)/B4 | C33: =(C21+C22)/C4 | D33: =(D21+D22)/D4 | E33: =(E21+E22)/E4 | F33: =(F21+F22)/F4 | G33: =(G21+G22)/G4
A34: Capex % revenue | B34: =-B22/B4 | C34: =-C22/C4 | D34: =-D22/D4 | E34: =-E22/E4 | F34: =-F22/F4 | G34: =-G22/G4
A35: International % revenue | B35: =B6/B4 | C35: =C6/C4 | D35: =D6/D4 | E35: =E6/E4 | F35: =F6/F4 | G35: =G6/G4
A36: Effective tax rate | B36: =B17/B16 | C36: =C17/C16 | D36: =D17/D16 | E36: =E17/E16 | F36: =F17/F16 | G36: =G17/G16
A38: Valuation history (CapIQ, quarterly averages of daily multiples)
B39: CQ4-24 | C39: CQ1-25 | D39: CQ2-25 | E39: CQ3-25 | F39: CQ4-25 | G39: CQ1-26 | H39: CQ2-26 | I39: CQ3-26*
A40: TEV / NTM EBITDA (avg) | B40: 25.8 | C40: 24.5 | D40: 23.8 | E40: 19.6 | F40: 17 | G40: 15.4 | H40: 13 | I40: 11.9 | J40: =AVERAGE(B40:I40) | K40: 2-yr avg
A41: P / NTM EPS (avg) | B41: 36.1 | C41: 34.5 | D41: 33.7 | E41: 28.4 | F41: 24.6 | G41: 22.9 | H41: 20 | I41: 18.5 | J41: =AVERAGE(B41:I41) | K41: 2-yr avg
A42: TEV / NTM revenue (avg) | B42: 11 | C42: 10.5 | D42: 10.2 | E42: 8.4 | F42: 7.3 | G42: 6.6 | H42: 5.5 | I42: 5 | J42: =AVERAGE(B42:I42) | K42: 2-yr avg
A43: * quarter-to-date through 24-Sep-2026. Source: Capital IQ 'Multiples' tab of provided export.

Sheet Model
A1: OPERATING MODEL - ACTIVE SCENARIO (change Inputs!B17) | $M, FY ends Jul-31 | H1: =CHOOSE(Inputs!$B$17,"BEAR","BASE","BULL")
B2: FY26A | C2: FY27E | D2: FY28E | E2: FY29E | F2: FY30E | G2: FY31E
A3: Core Copart (ex-ACV)
A4: US revenue | B4: 3807.4 | C4: =B4*(1+Inputs!$B$26)*(1+Inputs!$B$38) | D4: =C4*(1+Inputs!$C$26)*(1+Inputs!$C$38) | E4: =D4*(1+Inputs!$D$26)*(1+Inputs!$D$38) | F4: =E4*(1+Inputs!$E$26)*(1+Inputs!$E$38) | G4: =F4*(1+Inputs!$F$26)*(1+Inputs!$F$38)
A5: International revenue | B5: 858.8 | C5: =B5*(1+Inputs!$B$32)*(1+Inputs!$B$38) | D5: =C5*(1+Inputs!$C$32)*(1+Inputs!$C$38) | E5: =D5*(1+Inputs!$D$32)*(1+Inputs!$D$38) | F5: =E5*(1+Inputs!$E$32)*(1+Inputs!$E$38) | G5: =F5*(1+Inputs!$F$32)*(1+Inputs!$F$38)
A6: Core revenue | B6: =B4+B5 | C6: =C4+C5 | D6: =D4+D5 | E6: =E4+E5 | F6: =F4+F5 | G6: =G4+G5
A7: growth | C7: =C6/B6-1 | D7: =D6/C6-1 | E7: =E6/D6-1 | F7: =F6/E6-1 | G7: =G6/F6-1
A8: Core EBIT margin | B8: =B9/B6 | C8: =Inputs!$B$44 | D8: =Inputs!$C$44 | E8: =Inputs!$D$44 | F8: =Inputs!$E$44 | G8: =Inputs!$F$44
A9: Core EBIT | B9: 1652.6 | C9: =C6*C8 | D9: =D6*D8 | E9: =E6*E8 | F9: =F6*F8 | G9: =G6*G8
A10: Core D&A | B10: 229.4 | C10: =C6*Inputs!$B$50 | D10: =D6*Inputs!$C$50 | E10: =E6*Inputs!$D$50 | F10: =F6*Inputs!$E$50 | G10: =G6*Inputs!$F$50
A11: Core capex | B11: 337.4 | C11: =C6*Inputs!$B$56 | D11: =D6*Inputs!$C$56 | E11: =E6*Inputs!$D$56 | F11: =F6*Inputs!$E$56 | G11: =G6*Inputs!$F$56
A12: ACV Auctions (consolidated from close; CY figures used as FY proxy)
A13: Consolidation factor (share of year) | B13: 0 | C13: =Inputs!$B$118/12 | D13: =1 | E13: =1 | F13: =1 | G13: =1
A14: ACV revenue (annualized run-rate) | C14: =Inputs!$B$119*(1+Inputs!$B$104) | D14: =C14*(1+Inputs!$C$104) | E14: =D14*(1+Inputs!$D$104) | F14: =E14*(1+Inputs!$E$104) | G14: =F14*(1+Inputs!$F$104)
A15: ACV revenue consolidated | B15: 0 | C15: =C14*C13 | D15: =D14*D13 | E15: =E14*E13 | F15: =F14*F13 | G15: =G14*G13
A16: ACV adj. EBITDA (standalone) | C16: =C15*Inputs!$B$110 | D16: =D15*Inputs!$C$110 | E16: =E15*Inputs!$D$110 | F16: =F15*Inputs!$E$110 | G16: =G15*Inputs!$F$110
A17: less: ACV SBC | C17: =-Inputs!$B$120*(1+Inputs!$B$125)^1*C13 | D17: =-Inputs!$B$120*(1+Inputs!$B$125)^2*D13 | E17: =-Inputs!$B$120*(1+Inputs!$B$125)^3*E13 | F17: =-Inputs!$B$120*(1+Inputs!$B$125)^4*F13 | G17: =-Inputs!$B$120*(1+Inputs!$B$125)^5*G13
A18: less: ACV existing D&A | C18: =-Inputs!$B$121*(1+Inputs!$B$125)^1*C13 | D18: =-Inputs!$B$121*(1+Inputs!$B$125)^2*D13 | E18: =-Inputs!$B$121*(1+Inputs!$B$125)^3*E13 | F18: =-Inputs!$B$121*(1+Inputs!$B$125)^4*F13 | G18: =-Inputs!$B$121*(1+Inputs!$B$125)^5*G13
A19: less: acquired-intangible amortization | C19: =-Inputs!$B$124*C13 | D19: =-Inputs!$B$124*D13 | E19: =-Inputs!$B$124*E13 | F19: =-Inputs!$B$124*F13 | G19: =-Inputs!$B$124*G13
A20: plus: synergies (pre-tax) | C20: =Inputs!$B$98 | D20: =Inputs!$C$98 | E20: =Inputs!$D$98 | F20: =Inputs!$E$98 | G20: =Inputs!$F$98
A21: ACV EBIT contribution (GAAP) | B21: 0 | C21: =SUM(C16:C20) | D21: =SUM(D16:D20) | E21: =SUM(E16:E20) | F21: =SUM(F16:F20) | G21: =SUM(G16:G20)
A22: ACV D&A (total) | B22: 0 | C22: =-C18-C19 | D22: =-D18-D19 | E22: =-E18-E19 | F22: =-F18-F19 | G22: =-G18-G19
A23: ACV capex | B23: 0 | C23: =C15*0.02 | D23: =D15*0.02 | E23: =E15*0.02 | F23: =F15*0.02 | G23: =G15*0.02
A24: Consolidated P&L
A25: Total revenue | B25: =B6 | C25: =C6+C15 | D25: =D6+D15 | E25: =E6+E15 | F25: =F6+F15 | G25: =G6+G15
A26: growth | C26: =C25/B25-1 | D26: =D25/C25-1 | E26: =E25/D25-1 | F26: =F25/E25-1 | G26: =G25/F25-1
A27: EBIT | B27: =B9 | C27: =C9+C21 | D27: =D9+D21 | E27: =E9+E21 | F27: =F9+F21 | G27: =G9+G21
A28: EBIT margin | B28: =B27/B25 | C28: =C27/C25 | D28: =D27/D25 | E28: =E27/E25 | F28: =F27/F25 | G28: =G27/G25
A29: D&A | B29: =B10 | C29: =C10+C22 | D29: =D10+D22 | E29: =E10+E22 | F29: =F10+F22 | G29: =G10+G22
A30: EBITDA | B30: =B27+B29 | C30: =C27+C29 | D30: =D27+D29 | E30: =E27+E29 | F30: =F27+F29 | G30: =G27+G29
A31: Interest income on cash | B31: 181.9 | C31: =(B44+C42+C43)*Inputs!$B$74 | D31: =(C44+D42+D43)*Inputs!$C$74 | E31: =(D44+E42+E43)*Inputs!$D$74 | F31: =(E44+F42+F43)*Inputs!$E$74 | G31: =(F44+G42+G43)*Inputs!$F$74 | I31: On beginning cash less buybacks & ACV outlay (avoids circularity)
A32: Pre-tax income | B32: 1835 | C32: =C27+C31 | D32: =D27+D31 | E32: =E27+E31 | F32: =F27+F31 | G32: =G27+G31
A33: Tax | B33: -354.6 | C33: =-C32*Inputs!$B$68 | D33: =-D32*Inputs!$C$68 | E33: =-E32*Inputs!$D$68 | F33: =-F32*Inputs!$E$68 | G33: =-G32*Inputs!$F$68
A34: Net income | B34: 1484.3 | C34: =C32+C33 | D34: =D32+D33 | E34: =E32+E33 | F34: =F32+F33 | G34: =G32+G33
A35: Diluted shares (M, avg) | B35: 956.86 | C35: =AVERAGE(B46,C46) | D35: =AVERAGE(C46,D46) | E35: =AVERAGE(D46,E46) | F35: =AVERAGE(E46,F46) | G35: =AVERAGE(F46,G46)
A36: Diluted EPS ($) | B36: 1.55 | C36: =C34/C35 | D36: =D34/D35 | E36: =E34/E35 | F36: =F34/F35 | G36: =G34/G35
A37: EPS growth | C37: =C36/B36-1 | D37: =D36/C36-1 | E37: =E36/D36-1 | F37: =F36/E36-1 | G37: =G36/F36-1
A38: Cash EPS (ex acquired-intangible amort., $) | B38: 1.55 | C38: =(C34-C19*(1-Inputs!$B$68))/C35 | D38: =(D34-D19*(1-Inputs!$C$68))/D35 | E38: =(E34-E19*(1-Inputs!$D$68))/E35 | F38: =(F34-F19*(1-Inputs!$E$68))/F35 | G38: =(G34-G19*(1-Inputs!$F$68))/G35
A39: Cash flow & share count
A40: Unlevered FCF (EBIT*(1-t) + D&A - capex - dNWC) | C40: =C27*(1-Inputs!$B$68)+C29-C11-C23-(C25-B25)*Inputs!$B$62 | D40: =D27*(1-Inputs!$C$68)+D29-D11-D23-(D25-C25)*Inputs!$C$62 | E40: =E27*(1-Inputs!$D$68)+E29-E11-E23-(E25-D25)*Inputs!$D$62 | F40: =F27*(1-Inputs!$E$68)+F29-F11-F23-(F25-E25)*Inputs!$E$62 | G40: =G27*(1-Inputs!$F$68)+G29-G11-G23-(G25-F25)*Inputs!$F$62
A41: Levered FCF (NI + D&A - capex - dNWC) | B41: 1376.3 | C41: =C34+C29-C11-C23-(C25-B25)*Inputs!$B$62 | D41: =D34+D29-D11-D23-(D25-C25)*Inputs!$C$62 | E41: =E34+E29-E11-E23-(E25-D25)*Inputs!$D$62 | F41: =F34+F29-F11-F23-(F25-E25)*Inputs!$E$62 | G41: =G34+G29-G11-G23-(G25-F25)*Inputs!$F$62
A42: Share buybacks | B42: -1636.3 | C42: =-Inputs!$B$80 | D42: =-Inputs!$C$80 | E42: =-Inputs!$D$80 | F42: =-Inputs!$E$80 | G42: =-Inputs!$F$80
A43: ACV acquisition | B43: 0 | C43: =-Inputs!$B$116 | D43: =0 | E43: =0 | F43: =0 | G43: =0
A44: Ending cash & investments | B44: 4489.8 | C44: =B44+C41+C42+C43 | D44: =C44+D41+D42+D43 | E44: =D44+E41+E42+E43 | F44: =E44+F41+F42+F43 | G44: =F44+G41+G42+G43
A45: Shares repurchased (M) | C45: =Inputs!$B$80/Inputs!$B$86 | D45: =Inputs!$C$80/Inputs!$C$86 | E45: =Inputs!$D$80/Inputs!$D$86 | F45: =Inputs!$E$80/Inputs!$E$86 | G45: =Inputs!$F$80/Inputs!$F$86
A46: Ending diluted shares (M) | B46: 927 | C46: =B46*(1+Inputs!$B$92)-C45 | D46: =C46*(1+Inputs!$C$92)-D45 | E46: =D46*(1+Inputs!$D$92)-E45 | F46: =E46*(1+Inputs!$E$92)-F45 | G46: =F46*(1+Inputs!$F$92)-G45 | I46: FY26 end-point: 925.8M basic + ~1M dilution

Sheet Scenarios
A1: BEAR CASE - full model
B2: FY26A | C2: FY27E | D2: FY28E | E2: FY29E | F2: FY30E | G2: FY31E
A3: Core Copart (ex-ACV)
A4: US revenue | B4: 3807.4 | C4: =B4*(1+Inputs!$B$23)*(1+Inputs!$B$35) | D4: =C4*(1+Inputs!$C$23)*(1+Inputs!$C$35) | E4: =D4*(1+Inputs!$D$23)*(1+Inputs!$D$35) | F4: =E4*(1+Inputs!$E$23)*(1+Inputs!$E$35) | G4: =F4*(1+Inputs!$F$23)*(1+Inputs!$F$35)
A5: International revenue | B5: 858.8 | C5: =B5*(1+Inputs!$B$29)*(1+Inputs!$B$35) | D5: =C5*(1+Inputs!$C$29)*(1+Inputs!$C$35) | E5: =D5*(1+Inputs!$D$29)*(1+Inputs!$D$35) | F5: =E5*(1+Inputs!$E$29)*(1+Inputs!$E$35) | G5: =F5*(1+Inputs!$F$29)*(1+Inputs!$F$35)
A6: Core revenue | B6: =B4+B5 | C6: =C4+C5 | D6: =D4+D5 | E6: =E4+E5 | F6: =F4+F5 | G6: =G4+G5
A7: growth | C7: =C6/B6-1 | D7: =D6/C6-1 | E7: =E6/D6-1 | F7: =F6/E6-1 | G7: =G6/F6-1
A8: Core EBIT margin | B8: =B9/B6 | C8: =Inputs!$B$41 | D8: =Inputs!$C$41 | E8: =Inputs!$D$41 | F8: =Inputs!$E$41 | G8: =Inputs!$F$41
A9: Core EBIT | B9: 1652.6 | C9: =C6*C8 | D9: =D6*D8 | E9: =E6*E8 | F9: =F6*F8 | G9: =G6*G8
A10: Core D&A | B10: 229.4 | C10: =C6*Inputs!$B$47 | D10: =D6*Inputs!$C$47 | E10: =E6*Inputs!$D$47 | F10: =F6*Inputs!$E$47 | G10: =G6*Inputs!$F$47
A11: Core capex | B11: 337.4 | C11: =C6*Inputs!$B$53 | D11: =D6*Inputs!$C$53 | E11: =E6*Inputs!$D$53 | F11: =F6*Inputs!$E$53 | G11: =G6*Inputs!$F$53
A12: ACV Auctions (consolidated from close; CY figures used as FY proxy)
A13: Consolidation factor (share of year) | B13: 0 | C13: =Inputs!$B$118/12 | D13: =1 | E13: =1 | F13: =1 | G13: =1
A14: ACV revenue (annualized run-rate) | C14: =Inputs!$B$119*(1+Inputs!$B$101) | D14: =C14*(1+Inputs!$C$101) | E14: =D14*(1+Inputs!$D$101) | F14: =E14*(1+Inputs!$E$101) | G14: =F14*(1+Inputs!$F$101)
A15: ACV revenue consolidated | B15: 0 | C15: =C14*C13 | D15: =D14*D13 | E15: =E14*E13 | F15: =F14*F13 | G15: =G14*G13
A16: ACV adj. EBITDA (standalone) | C16: =C15*Inputs!$B$107 | D16: =D15*Inputs!$C$107 | E16: =E15*Inputs!$D$107 | F16: =F15*Inputs!$E$107 | G16: =G15*Inputs!$F$107
A17: less: ACV SBC | C17: =-Inputs!$B$120*(1+Inputs!$B$125)^1*C13 | D17: =-Inputs!$B$120*(1+Inputs!$B$125)^2*D13 | E17: =-Inputs!$B$120*(1+Inputs!$B$125)^3*E13 | F17: =-Inputs!$B$120*(1+Inputs!$B$125)^4*F13 | G17: =-Inputs!$B$120*(1+Inputs!$B$125)^5*G13
A18: less: ACV existing D&A | C18: =-Inputs!$B$121*(1+Inputs!$B$125)^1*C13 | D18: =-Inputs!$B$121*(1+Inputs!$B$125)^2*D13 | E18: =-Inputs!$B$121*(1+Inputs!$B$125)^3*E13 | F18: =-Inputs!$B$121*(1+Inputs!$B$125)^4*F13 | G18: =-Inputs!$B$121*(1+Inputs!$B$125)^5*G13
A19: less: acquired-intangible amortization | C19: =-Inputs!$B$124*C13 | D19: =-Inputs!$B$124*D13 | E19: =-Inputs!$B$124*E13 | F19: =-Inputs!$B$124*F13 | G19: =-Inputs!$B$124*G13
A20: plus: synergies (pre-tax) | C20: =Inputs!$B$95 | D20: =Inputs!$C$95 | E20: =Inputs!$D$95 | F20: =Inputs!$E$95 | G20: =Inputs!$F$95
A21: ACV EBIT contribution (GAAP) | B21: 0 | C21: =SUM(C16:C20) | D21: =SUM(D16:D20) | E21: =SUM(E16:E20) | F21: =SUM(F16:F20) | G21: =SUM(G16:G20)
A22: ACV D&A (total) | B22: 0 | C22: =-C18-C19 | D22: =-D18-D19 | E22: =-E18-E19 | F22: =-F18-F19 | G22: =-G18-G19
A23: ACV capex | B23: 0 | C23: =C15*0.02 | D23: =D15*0.02 | E23: =E15*0.02 | F23: =F15*0.02 | G23: =G15*0.02
A24: Consolidated P&L
A25: Total revenue | B25: =B6 | C25: =C6+C15 | D25: =D6+D15 | E25: =E6+E15 | F25: =F6+F15 | G25: =G6+G15
A26: growth | C26: =C25/B25-1 | D26: =D25/C25-1 | E26: =E25/D25-1 | F26: =F25/E25-1 | G26: =G25/F25-1
A27: EBIT | B27: =B9 | C27: =C9+C21 | D27: =D9+D21 | E27: =E9+E21 | F27: =F9+F21 | G27: =G9+G21
A28: EBIT margin | B28: =B27/B25 | C28: =C27/C25 | D28: =D27/D25 | E28: =E27/E25 | F28: =F27/F25 | G28: =G27/G25
A29: D&A | B29: =B10 | C29: =C10+C22 | D29: =D10+D22 | E29: =E10+E22 | F29: =F10+F22 | G29: =G10+G22
A30: EBITDA | B30: =B27+B29 | C30: =C27+C29 | D30: =D27+D29 | E30: =E27+E29 | F30: =F27+F29 | G30: =G27+G29
A31: Interest income on cash | B31: 181.9 | C31: =(B44+C42+C43)*Inputs!$B$71 | D31: =(C44+D42+D43)*Inputs!$C$71 | E31: =(D44+E42+E43)*Inputs!$D$71 | F31: =(E44+F42+F43)*Inputs!$E$71 | G31: =(F44+G42+G43)*Inputs!$F$71 | I31: On beginning cash less buybacks & ACV outlay (avoids circularity)
A32: Pre-tax income | B32: 1835 | C32: =C27+C31 | D32: =D27+D31 | E32: =E27+E31 | F32: =F27+F31 | G32: =G27+G31
A33: Tax | B33: -354.6 | C33: =-C32*Inputs!$B$65 | D33: =-D32*Inputs!$C$65 | E33: =-E32*Inputs!$D$65 | F33: =-F32*Inputs!$E$65 | G33: =-G32*Inputs!$F$65
A34: Net income | B34: 1484.3 | C34: =C32+C33 | D34: =D32+D33 | E34: =E32+E33 | F34: =F32+F33 | G34: =G32+G33
A35: Diluted shares (M, avg) | B35: 956.86 | C35: =AVERAGE(B46,C46) | D35: =AVERAGE(C46,D46) | E35: =AVERAGE(D46,E46) | F35: =AVERAGE(E46,F46) | G35: =AVERAGE(F46,G46)
A36: Diluted EPS ($) | B36: 1.55 | C36: =C34/C35 | D36: =D34/D35 | E36: =E34/E35 | F36: =F34/F35 | G36: =G34/G35
A37: EPS growth | C37: =C36/B36-1 | D37: =D36/C36-1 | E37: =E36/D36-1 | F37: =F36/E36-1 | G37: =G36/F36-1
A38: Cash EPS (ex acquired-intangible amort., $) | B38: 1.55 | C38: =(C34-C19*(1-Inputs!$B$65))/C35 | D38: =(D34-D19*(1-Inputs!$C$65))/D35 | E38: =(E34-E19*(1-Inputs!$D$65))/E35 | F38: =(F34-F19*(1-Inputs!$E$65))/F35 | G38: =(G34-G19*(1-Inputs!$F$65))/G35
A39: Cash flow & share count
A40: Unlevered FCF (EBIT*(1-t) + D&A - capex - dNWC) | C40: =C27*(1-Inputs!$B$65)+C29-C11-C23-(C25-B25)*Inputs!$B$59 | D40: =D27*(1-Inputs!$C$65)+D29-D11-D23-(D25-C25)*Inputs!$C$59 | E40: =E27*(1-Inputs!$D$65)+E29-E11-E23-(E25-D25)*Inputs!$D$59 | F40: =F27*(1-Inputs!$E$65)+F29-F11-F23-(F25-E25)*Inputs!$E$59 | G40: =G27*(1-Inputs!$F$65)+G29-G11-G23-(G25-F25)*Inputs!$F$59
A41: Levered FCF (NI + D&A - capex - dNWC) | B41: 1376.3 | C41: =C34+C29-C11-C23-(C25-B25)*Inputs!$B$59 | D41: =D34+D29-D11-D23-(D25-C25)*Inputs!$C$59 | E41: =E34+E29-E11-E23-(E25-D25)*Inputs!$D$59 | F41: =F34+F29-F11-F23-(F25-E25)*Inputs!$E$59 | G41: =G34+G29-G11-G23-(G25-F25)*Inputs!$F$59
A42: Share buybacks | B42: -1636.3 | C42: =-Inputs!$B$77 | D42: =-Inputs!$C$77 | E42: =-Inputs!$D$77 | F42: =-Inputs!$E$77 | G42: =-Inputs!$F$77
A43: ACV acquisition | B43: 0 | C43: =-Inputs!$B$116 | D43: =0 | E43: =0 | F43: =0 | G43: =0
A44: Ending cash & investments | B44: 4489.8 | C44: =B44+C41+C42+C43 | D44: =C44+D41+D42+D43 | E44: =D44+E41+E42+E43 | F44: =E44+F41+F42+F43 | G44: =F44+G41+G42+G43
A45: Shares repurchased (M) | C45: =Inputs!$B$77/Inputs!$B$83 | D45: =Inputs!$C$77/Inputs!$C$83 | E45: =Inputs!$D$77/Inputs!$D$83 | F45: =Inputs!$E$77/Inputs!$E$83 | G45: =Inputs!$F$77/Inputs!$F$83
A46: Ending diluted shares (M) | B46: 927 | C46: =B46*(1+Inputs!$B$89)-C45 | D46: =C46*(1+Inputs!$C$89)-D45 | E46: =D46*(1+Inputs!$D$89)-E45 | F46: =E46*(1+Inputs!$E$89)-F45 | G46: =F46*(1+Inputs!$F$89)-G45 | I46: FY26 end-point: 925.8M basic + ~1M dilution
A48: BASE CASE - full model
B49: FY26A | C49: FY27E | D49: FY28E | E49: FY29E | F49: FY30E | G49: FY31E
A50: Core Copart (ex-ACV)
A51: US revenue | B51: 3807.4 | C51: =B51*(1+Inputs!$B$24)*(1+Inputs!$B$36) | D51: =C51*(1+Inputs!$C$24)*(1+Inputs!$C$36) | E51: =D51*(1+Inputs!$D$24)*(1+Inputs!$D$36) | F51: =E51*(1+Inputs!$E$24)*(1+Inputs!$E$36) | G51: =F51*(1+Inputs!$F$24)*(1+Inputs!$F$36)
A52: International revenue | B52: 858.8 | C52: =B52*(1+Inputs!$B$30)*(1+Inputs!$B$36) | D52: =C52*(1+Inputs!$C$30)*(1+Inputs!$C$36) | E52: =D52*(1+Inputs!$D$30)*(1+Inputs!$D$36) | F52: =E52*(1+Inputs!$E$30)*(1+Inputs!$E$36) | G52: =F52*(1+Inputs!$F$30)*(1+Inputs!$F$36)
A53: Core revenue | B53: =B51+B52 | C53: =C51+C52 | D53: =D51+D52 | E53: =E51+E52 | F53: =F51+F52 | G53: =G51+G52
A54: growth | C54: =C53/B53-1 | D54: =D53/C53-1 | E54: =E53/D53-1 | F54: =F53/E53-1 | G54: =G53/F53-1
A55: Core EBIT margin | B55: =B56/B53 | C55: =Inputs!$B$42 | D55: =Inputs!$C$42 | E55: =Inputs!$D$42 | F55: =Inputs!$E$42 | G55: =Inputs!$F$42
A56: Core EBIT | B56: 1652.6 | C56: =C53*C55 | D56: =D53*D55 | E56: =E53*E55 | F56: =F53*F55 | G56: =G53*G55
A57: Core D&A | B57: 229.4 | C57: =C53*Inputs!$B$48 | D57: =D53*Inputs!$C$48 | E57: =E53*Inputs!$D$48 | F57: =F53*Inputs!$E$48 | G57: =G53*Inputs!$F$48
A58: Core capex | B58: 337.4 | C58: =C53*Inputs!$B$54 | D58: =D53*Inputs!$C$54 | E58: =E53*Inputs!$D$54 | F58: =F53*Inputs!$E$54 | G58: =G53*Inputs!$F$54
A59: ACV Auctions (consolidated from close; CY figures used as FY proxy)
A60: Consolidation factor (share of year) | B60: 0 | C60: =Inputs!$B$118/12 | D60: =1 | E60: =1 | F60: =1 | G60: =1
A61: ACV revenue (annualized run-rate) | C61: =Inputs!$B$119*(1+Inputs!$B$102) | D61: =C61*(1+Inputs!$C$102) | E61: =D61*(1+Inputs!$D$102) | F61: =E61*(1+Inputs!$E$102) | G61: =F61*(1+Inputs!$F$102)
A62: ACV revenue consolidated | B62: 0 | C62: =C61*C60 | D62: =D61*D60 | E62: =E61*E60 | F62: =F61*F60 | G62: =G61*G60
A63: ACV adj. EBITDA (standalone) | C63: =C62*Inputs!$B$108 | D63: =D62*Inputs!$C$108 | E63: =E62*Inputs!$D$108 | F63: =F62*Inputs!$E$108 | G63: =G62*Inputs!$F$108
A64: less: ACV SBC | C64: =-Inputs!$B$120*(1+Inputs!$B$125)^1*C60 | D64: =-Inputs!$B$120*(1+Inputs!$B$125)^2*D60 | E64: =-Inputs!$B$120*(1+Inputs!$B$125)^3*E60 | F64: =-Inputs!$B$120*(1+Inputs!$B$125)^4*F60 | G64: =-Inputs!$B$120*(1+Inputs!$B$125)^5*G60
A65: less: ACV existing D&A | C65: =-Inputs!$B$121*(1+Inputs!$B$125)^1*C60 | D65: =-Inputs!$B$121*(1+Inputs!$B$125)^2*D60 | E65: =-Inputs!$B$121*(1+Inputs!$B$125)^3*E60 | F65: =-Inputs!$B$121*(1+Inputs!$B$125)^4*F60 | G65: =-Inputs!$B$121*(1+Inputs!$B$125)^5*G60
A66: less: acquired-intangible amortization | C66: =-Inputs!$B$124*C60 | D66: =-Inputs!$B$124*D60 | E66: =-Inputs!$B$124*E60 | F66: =-Inputs!$B$124*F60 | G66: =-Inputs!$B$124*G60
A67: plus: synergies (pre-tax) | C67: =Inputs!$B$96 | D67: =Inputs!$C$96 | E67: =Inputs!$D$96 | F67: =Inputs!$E$96 | G67: =Inputs!$F$96
A68: ACV EBIT contribution (GAAP) | B68: 0 | C68: =SUM(C63:C67) | D68: =SUM(D63:D67) | E68: =SUM(E63:E67) | F68: =SUM(F63:F67) | G68: =SUM(G63:G67)
A69: ACV D&A (total) | B69: 0 | C69: =-C65-C66 | D69: =-D65-D66 | E69: =-E65-E66 | F69: =-F65-F66 | G69: =-G65-G66
A70: ACV capex | B70: 0 | C70: =C62*0.02 | D70: =D62*0.02 | E70: =E62*0.02 | F70: =F62*0.02 | G70: =G62*0.02
A71: Consolidated P&L
A72: Total revenue | B72: =B53 | C72: =C53+C62 | D72: =D53+D62 | E72: =E53+E62 | F72: =F53+F62 | G72: =G53+G62
A73: growth | C73: =C72/B72-1 | D73: =D72/C72-1 | E73: =E72/D72-1 | F73: =F72/E72-1 | G73: =G72/F72-1
A74: EBIT | B74: =B56 | C74: =C56+C68 | D74: =D56+D68 | E74: =E56+E68 | F74: =F56+F68 | G74: =G56+G68
A75: EBIT margin | B75: =B74/B72 | C75: =C74/C72 | D75: =D74/D72 | E75: =E74/E72 | F75: =F74/F72 | G75: =G74/G72
A76: D&A | B76: =B57 | C76: =C57+C69 | D76: =D57+D69 | E76: =E57+E69 | F76: =F57+F69 | G76: =G57+G69
A77: EBITDA | B77: =B74+B76 | C77: =C74+C76 | D77: =D74+D76 | E77: =E74+E76 | F77: =F74+F76 | G77: =G74+G76
A78: Interest income on cash | B78: 181.9 | C78: =(B91+C89+C90)*Inputs!$B$72 | D78: =(C91+D89+D90)*Inputs!$C$72 | E78: =(D91+E89+E90)*Inputs!$D$72 | F78: =(E91+F89+F90)*Inputs!$E$72 | G78: =(F91+G89+G90)*Inputs!$F$72 | I78: On beginning cash less buybacks & ACV outlay (avoids circularity)
A79: Pre-tax income | B79: 1835 | C79: =C74+C78 | D79: =D74+D78 | E79: =E74+E78 | F79: =F74+F78 | G79: =G74+G78
A80: Tax | B80: -354.6 | C80: =-C79*Inputs!$B$66 | D80: =-D79*Inputs!$C$66 | E80: =-E79*Inputs!$D$66 | F80: =-F79*Inputs!$E$66 | G80: =-G79*Inputs!$F$66
A81: Net income | B81: 1484.3 | C81: =C79+C80 | D81: =D79+D80 | E81: =E79+E80 | F81: =F79+F80 | G81: =G79+G80
A82: Diluted shares (M, avg) | B82: 956.86 | C82: =AVERAGE(B93,C93) | D82: =AVERAGE(C93,D93) | E82: =AVERAGE(D93,E93) | F82: =AVERAGE(E93,F93) | G82: =AVERAGE(F93,G93)
A83: Diluted EPS ($) | B83: 1.55 | C83: =C81/C82 | D83: =D81/D82 | E83: =E81/E82 | F83: =F81/F82 | G83: =G81/G82
A84: EPS growth | C84: =C83/B83-1 | D84: =D83/C83-1 | E84: =E83/D83-1 | F84: =F83/E83-1 | G84: =G83/F83-1
A85: Cash EPS (ex acquired-intangible amort., $) | B85: 1.55 | C85: =(C81-C66*(1-Inputs!$B$66))/C82 | D85: =(D81-D66*(1-Inputs!$C$66))/D82 | E85: =(E81-E66*(1-Inputs!$D$66))/E82 | F85: =(F81-F66*(1-Inputs!$E$66))/F82 | G85: =(G81-G66*(1-Inputs!$F$66))/G82
A86: Cash flow & share count
A87: Unlevered FCF (EBIT*(1-t) + D&A - capex - dNWC) | C87: =C74*(1-Inputs!$B$66)+C76-C58-C70-(C72-B72)*Inputs!$B$60 | D87: =D74*(1-Inputs!$C$66)+D76-D58-D70-(D72-C72)*Inputs!$C$60 | E87: =E74*(1-Inputs!$D$66)+E76-E58-E70-(E72-D72)*Inputs!$D$60 | F87: =F74*(1-Inputs!$E$66)+F76-F58-F70-(F72-E72)*Inputs!$E$60 | G87: =G74*(1-Inputs!$F$66)+G76-G58-G70-(G72-F72)*Inputs!$F$60
A88: Levered FCF (NI + D&A - capex - dNWC) | B88: 1376.3 | C88: =C81+C76-C58-C70-(C72-B72)*Inputs!$B$60 | D88: =D81+D76-D58-D70-(D72-C72)*Inputs!$C$60 | E88: =E81+E76-E58-E70-(E72-D72)*Inputs!$D$60 | F88: =F81+F76-F58-F70-(F72-E72)*Inputs!$E$60 | G88: =G81+G76-G58-G70-(G72-F72)*Inputs!$F$60
A89: Share buybacks | B89: -1636.3 | C89: =-Inputs!$B$78 | D89: =-Inputs!$C$78 | E89: =-Inputs!$D$78 | F89: =-Inputs!$E$78 | G89: =-Inputs!$F$78
A90: ACV acquisition | B90: 0 | C90: =-Inputs!$B$116 | D90: =0 | E90: =0 | F90: =0 | G90: =0
A91: Ending cash & investments | B91: 4489.8 | C91: =B91+C88+C89+C90 | D91: =C91+D88+D89+D90 | E91: =D91+E88+E89+E90 | F91: =E91+F88+F89+F90 | G91: =F91+G88+G89+G90
A92: Shares repurchased (M) | C92: =Inputs!$B$78/Inputs!$B$84 | D92: =Inputs!$C$78/Inputs!$C$84 | E92: =Inputs!$D$78/Inputs!$D$84 | F92: =Inputs!$E$78/Inputs!$E$84 | G92: =Inputs!$F$78/Inputs!$F$84
A93: Ending diluted shares (M) | B93: 927 | C93: =B93*(1+Inputs!$B$90)-C92 | D93: =C93*(1+Inputs!$C$90)-D92 | E93: =D93*(1+Inputs!$D$90)-E92 | F93: =E93*(1+Inputs!$E$90)-F92 | G93: =F93*(1+Inputs!$F$90)-G92 | I93: FY26 end-point: 925.8M basic + ~1M dilution
A95: BULL CASE - full model
B96: FY26A | C96: FY27E | D96: FY28E | E96: FY29E | F96: FY30E | G96: FY31E
A97: Core Copart (ex-ACV)
A98: US revenue | B98: 3807.4 | C98: =B98*(1+Inputs!$B$25)*(1+Inputs!$B$37) | D98: =C98*(1+Inputs!$C$25)*(1+Inputs!$C$37) | E98: =D98*(1+Inputs!$D$25)*(1+Inputs!$D$37) | F98: =E98*(1+Inputs!$E$25)*(1+Inputs!$E$37) | G98: =F98*(1+Inputs!$F$25)*(1+Inputs!$F$37)
A99: International revenue | B99: 858.8 | C99: =B99*(1+Inputs!$B$31)*(1+Inputs!$B$37) | D99: =C99*(1+Inputs!$C$31)*(1+Inputs!$C$37) | E99: =D99*(1+Inputs!$D$31)*(1+Inputs!$D$37) | F99: =E99*(1+Inputs!$E$31)*(1+Inputs!$E$37) | G99: =F99*(1+Inputs!$F$31)*(1+Inputs!$F$37)
A100: Core revenue | B100: =B98+B99 | C100: =C98+C99 | D100: =D98+D99 | E100: =E98+E99 | F100: =F98+F99 | G100: =G98+G99
A101: growth | C101: =C100/B100-1 | D101: =D100/C100-1 | E101: =E100/D100-1 | F101: =F100/E100-1 | G101: =G100/F100-1
A102: Core EBIT margin | B102: =B103/B100 | C102: =Inputs!$B$43 | D102: =Inputs!$C$43 | E102: =Inputs!$D$43 | F102: =Inputs!$E$43 | G102: =Inputs!$F$43
...

Sheet Valuation
A1: 12-MONTH TARGET PRICE - SCENARIO ANALYSIS (target date ~Sep-2027; NTM = FY28E)
B2: Bear | C2: Base | D2: Bull | E2: Prob-wtd | F2: Notes
A3: Probability | B3: =Inputs!B$21 | C3: =Inputs!C$21 | D3: =Inputs!D$21 | E3: =SUM(B3:D3)
A4: Operating outputs
A5: FY27E revenue | B5: =Scenarios!$C$25 | C5: =Scenarios!$C$72 | D5: =Scenarios!$C$119 | E5: =SUMPRODUCT(B5:D5,Inputs!$B$21:$D$21) | F5: Consensus FY27E $4,914M (CapIQ)
A6: FY28E revenue | B6: =Scenarios!$D$25 | C6: =Scenarios!$D$72 | D6: =Scenarios!$D$119 | E6: =SUMPRODUCT(B6:D6,Inputs!$B$21:$D$21) | F6: Consensus FY28E $5,306M (CapIQ)
A7: FY27E EPS | B7: =Scenarios!$C$36 | C7: =Scenarios!$C$83 | D7: =Scenarios!$C$130 | E7: =SUMPRODUCT(B7:D7,Inputs!$B$21:$D$21) | F7: Consensus FY27E $1.63
A8: FY28E EPS (NTM at target date) | B8: =Scenarios!$D$36 | C8: =Scenarios!$D$83 | D8: =Scenarios!$D$130 | E8: =SUMPRODUCT(B8:D8,Inputs!$B$21:$D$21) | F8: Consensus FY28E $1.77
A9: FY28E cash EPS (ex deal amortization) | B9: =Scenarios!$D$38 | C9: =Scenarios!$D$85 | D9: =Scenarios!$D$132 | E9: =SUMPRODUCT(B9:D9,Inputs!$B$21:$D$21)
A10: FY28E EBITDA | B10: =Scenarios!$D$30 | C10: =Scenarios!$D$77 | D10: =Scenarios!$D$124 | E10: =SUMPRODUCT(B10:D10,Inputs!$B$21:$D$21)
A11: FY27E ending net cash | B11: =Scenarios!$C$44-Inputs!$B$10-Inputs!$B$11 | C11: =Scenarios!$C$91-Inputs!$B$10-Inputs!$B$11 | D11: =Scenarios!$C$138-Inputs!$B$10-Inputs!$B$11 | E11: =SUMPRODUCT(B11:D11,Inputs!$B$21:$D$21) | F11: Post-ACV cash, post-buybacks
A12: FY27E ending diluted shares (M) | B12: =Scenarios!$C$46 | C12: =Scenarios!$C$93 | D12: =Scenarios!$C$140 | E12: =SUMPRODUCT(B12:D12,Inputs!$B$21:$D$21)
A13: Method 1: P/E on NTM EPS
A14: Target P/E | B14: =Inputs!$B$112 | C14: =Inputs!$C$112 | D14: =Inputs!$D$112 | F14: Current 17.7x NTM; 2-yr avg 27x
A15: Implied price (P/E) | B15: =B14*B8 | C15: =C14*C8 | D15: =D14*D8 | E15: =SUMPRODUCT(B15:D15,Inputs!$B$21:$D$21)
A16: Method 2: EV/EBITDA on NTM EBITDA
A17: Target EV/EBITDA | B17: =Inputs!$B$113 | C17: =Inputs!$C$113 | D17: =Inputs!$D$113 | F17: Current 11.3x NTM; 2-yr avg 18.9x
A18: Implied EV | B18: =B17*B10 | C18: =C17*C10 | D18: =D17*D10
A19: Implied equity value | B19: =B18+B11 | C19: =C18+C11 | D19: =D18+D11
A20: Implied price (EV/EBITDA) | B20: =B19/B12 | C20: =C19/C12 | D20: =D19/D12 | E20: =SUMPRODUCT(B20:D20,Inputs!$B$21:$D$21)
A21: Method 3: DCF (intrinsic, from DCF sheet - active scenario only)
A22: DCF value per share (active scenario) | B22: =IF(Inputs!$B$17=1,DCF!$B$30,"n/a - set selector") | C22: =IF(Inputs!$B$17=2,DCF!$B$30,"n/a - set selector") | D22: =IF(Inputs!$B$17=3,DCF!$B$30,"n/a - set selector") | F22: Run each scenario via Inputs!B17 to populate
A23: Blended 12-month target
A24: Weight: P/E method | B24: 0.5 | F24: Remaining weight to EV/EBITDA
A25: 12-month target price | B25: =$B$24*B15+(1-$B$24)*B20 | C25: =$B$24*C15+(1-$B$24)*C20 | D25: =$B$24*D15+(1-$B$24)*D20 | E25: =SUMPRODUCT(B25:D25,Inputs!$B$21:$D$21)
A26: Upside / (downside) vs current | B26: =B25/Inputs!$B$6-1 | C26: =C25/Inputs!$B$6-1 | D26: =D25/Inputs!$B$6-1 | E26: =E25/Inputs!$B$6-1
A27: Implied NTM P/E at target (check) | B27: =B25/B8 | C27: =C25/C8 | D27: =D25/D8
A28: Implied EV/NTM EBITDA at target (check) | B28: =(B25*B12-B11)/B10 | C28: =(C25*C12-C11)/C10 | D28: =(D25*D12-D11)/D10
A30: Risk / reward
A31: Current price | B31: =Inputs!$B$6
A32: Probability-weighted target | B32: =E25
A33: Probability-weighted expected return | B33: =E26
A34: Upside (bull) / downside (bear) ratio | B34: =(D25-Inputs!$B$6)/(Inputs!$B$6-B25)
A35: Current NTM P/E (FY27E consensus EPS $1.63) | B35: =Inputs!$B$6/1.63
A36: Current EV / FY26A EBITDA | B36: =Inputs!$B$13/1882
A38: Sensitivity: 12-month price = Target P/E x FY28E EPS
A39: FY28E EPS -> | B39: 1.45 | C39: 1.55 | D39: 1.65 | E39: 1.75 | F39: 1.85 | G39: 1.95
A40: 14 | B40: =$A40*B$39 | C40: =$A40*C$39 | D40: =$A40*D$39 | E40: =$A40*E$39 | F40: =$A40*F$39 | G40: =$A40*G$39
A41: 16 | B41: =$A41*B$39 | C41: =$A41*C$39 | D41: =$A41*D$39 | E41: =$A41*E$39 | F41: =$A41*F$39 | G41: =$A41*G$39
A42: 18 | B42: =$A42*B$39 | C42: =$A42*C$39 | D42: =$A42*D$39 | E42: =$A42*E$39 | F42: =$A42*F$39 | G42: =$A42*G$39
A43: 20 | B43: =$A43*B$39 | C43: =$A43*C$39 | D43: =$A43*D$39 | E43: =$A43*E$39 | F43: =$A43*F$39 | G43: =$A43*G$39
A44: 22 | B44: =$A44*B$39 | C44: =$A44*C$39 | D44: =$A44*D$39 | E44: =$A44*E$39 | F44: =$A44*F$39 | G44: =$A44*G$39
A45: 24 | B45: =$A45*B$39 | C45: =$A45*C$39 | D45: =$A45*D$39 | E45: =$A45*E$39 | F45: =$A45*F$39 | G45: =$A45*G$39
A46: 26 | B46: =$A46*B$39 | C46: =$A46*C$39 | D46: =$A46*D$39 | E46: =$A46*E$39 | F46: =$A46*F$39 | G46: =$A46*G$39
A47: 28 | B47: =$A47*B$39 | C47: =$A47*C$39 | D47: =$A47*D$39 | E47: =$A47*E$39 | F47: =$A47*F$39 | G47: =$A47*G$39
A48: 30 | B48: =$A48*B$39 | C48: =$A48*C$39 | D48: =$A48*D$39 | E48: =$A48*E$39 | F48: =$A48*F$39 | G48: =$A48*G$39
A49: Green = above current price; red = below

Sheet DCF
A1: DCF - ACTIVE SCENARIO (5-yr explicit, Gordon growth terminal) | $M | H1: =CHOOSE(Inputs!$B$17,"BEAR","BASE","BULL")
B3: FY27E | C3: FY28E | D3: FY29E | E3: FY30E | F3: FY31E
A4: Unlevered FCF | B4: =Model!C40 | C4: =Model!D40 | D4: =Model!E40 | E4: =Model!F40 | F4: =Model!G40
A5: Discount period (yrs) | B5: =1-0.5*Inputs!$B$136 | C5: =2-0.5*Inputs!$B$136 | D5: =3-0.5*Inputs!$B$136 | E5: =4-0.5*Inputs!$B$136 | F5: =5-0.5*Inputs!$B$136
A6: Discount factor | B6: =1/(1+Inputs!$B$134)^B5 | C6: =1/(1+Inputs!$B$134)^C5 | D6: =1/(1+Inputs!$B$134)^D5 | E6: =1/(1+Inputs!$B$134)^E5 | F6: =1/(1+Inputs!$B$134)^F5
A7: PV of FCF | B7: =B4*B6 | C7: =C4*C6 | D7: =D4*D6 | E7: =E4*E6 | F7: =F4*F6
A9: WACC | B9: =Inputs!$B$134
A10: Terminal growth | B10: =Inputs!$B$135
A11: Terminal value (FY31 FCF x (1+g) / (WACC-g)) | B11: =F4*(1+B10)/(B9-B10)
A12: PV of terminal value | B12: =B11*F6
A13: Sum PV of FCF (FY27-31) | B13: =SUM(B7:F7)
A14: Enterprise value | B14: =B12+B13
A15: % of EV from terminal value | B15: =B12/B14
A16: Plus: cash & investments (31-Jul-26) | B16: =Inputs!$B$9
A17: Less: ACV purchase price (cash out at close) | B17: =-Inputs!$B$116
A18: Less: debt & minority interest | B18: =-Inputs!$B$10-Inputs!$B$11
A19: Equity value | B19: =SUM(B14,B16:B18)
A20: Diluted shares today (M) | B20: =Model!B46
A21: DCF value per share ($) | B21: =B19/B20
A22: Upside vs current | B22: =B21/Inputs!$B$6-1
A23: Implied EV / FY27E EBITDA | B23: =B14/Model!C30
A24: Implied terminal EV / FY31 EBITDA | B24: =B11/Model!G30
A30: DCF value per share (link) | B30: =B21
A32: Sensitivity: DCF value per share vs WACC (rows) and terminal growth (cols)
A33: WACC \ g | B33: 0.02 | C33: 0.025 | D33: 0.03 | E33: 0.035 | F33: 0.04
A34: 0.075 | B34: =(B$4/(1+$A34)^B$5+C$4/(1+$A34)^C$5+D$4/(1+$A34)^D$5+E$4/(1+$A34)^E$5+F$4/(1+$A34)^F$5+F$4*(1+B$33)/($A34-B$33)/(1+$A34)^F$5+$B$16+$B$17+$B$18)/$B$20 | C34: =(B$4/(1+$A34)^B$5+C$4/(1+$A34)^C$5+D$4/(1+$A34)^D$5+E$4/(1+$A34)^E$5+F$4/(1+$A34)^F$5+F$4*(1+C$33)/($A34-C$33)/(1+$A34)^F$5+$B$16+$B$17+$B$18)/$B$20 | D34: =(B$4/(1+$A34)^B$5+C$4/(1+$A34)^C$5+D$4/(1+$A34)^D$5+E$4/(1+$A34)^E$5+F$4/(1+$A34)^F$5+F$4*(1+D$33)/($A34-D$33)/(1+$A34)^F$5+$B$16+$B$17+$B$18)/$B$20 | E34: =(B$4/(1+$A34)^B$5+C$4/(1+$A34)^C$5+D$4/(1+$A34)^D$5+E$4/(1+$A34)^E$5+F$4/(1+$A34)^F$5+F$4*(1+E$33)/($A34-E$33)/(1+$A34)^F$5+$B$16+$B$17+$B$18)/$B$20 | F34: =(B$4/(1+$A34)^B$5+C$4/(1+$A34)^C$5+D$4/(1+$A34)^D$5+E$4/(1+$A34)^E$5+F$4/(1+$A34)^F$5+F$4*(1+F$33)/($A34-F$33)/(1+$A34)^F$5+$B$16+$B$17+$B$18)/$B$20
A35: 0.08 | B35: =(B$4/(1+$A35)^B$5+C$4/(1+$A35)^C$5+D$4/(1+$A35)^D$5+E$4/(1+$A35)^E$5+F$4/(1+$A35)^F$5+F$4*(1+B$33)/($A35-B$33)/(1+$A35)^F$5+$B$16+$B$17+$B$18)/$B$20 | C35: =(B$4/(1+$A35)^B$5+C$4/(1+$A35)^C$5+D$4/(1+$A35)^D$5+E$4/(1+$A35)^E$5+F$4/(1+$A35)^F$5+F$4*(1+C$33)/($A35-C$33)/(1+$A35)^F$5+$B$16+$B$17+$B$18)/$B$20 | D35: =(B$4/(1+$A35)^B$5+C$4/(1+$A35)^C$5+D$4/(1+$A35)^D$5+E$4/(1+$A35)^E$5+F$4/(1+$A35)^F$5+F$4*(1+D$33)/($A35-D$33)/(1+$A35)^F$5+$B$16+$B$17+$B$18)/$B$20 | E35: =(B$4/(1+$A35)^B$5+C$4/(1+$A35)^C$5+D$4/(1+$A35)^D$5+E$4/(1+$A35)^E$5+F$4/(1+$A35)^F$5+F$4*(1+E$33)/($A35-E$33)/(1+$A35)^F$5+$B$16+$B$17+$B$18)/$B$20 | F35: =(B$4/(1+$A35)^B$5+C$4/(1+$A35)^C$5+D$4/(1+$A35)^D$5+E$4/(1+$A35)^E$5+F$4/(1+$A35)^F$5+F$4*(1+F$33)/($A35-F$33)/(1+$A35)^F$5+$B$16+$B$17+$B$18)/$B$20
A36: 0.085 | B36: =(B$4/(1+$A36)^B$5+C$4/(1+$A36)^C$5+D$4/(1+$A36)^D$5+E$4/(1+$A36)^E$5+F$4/(1+$A36)^F$5+F$4*(1+B$33)/($A36-B$33)/(1+$A36)^F$5+$B$16+$B$17+$B$18)/$B$20 | C36: =(B$4/(1+$A36)^B$5+C$4/(1+$A36)^C$5+D$4/(1+$A36)^D$5+E$4/(1+$A36)^E$5+F$4/(1+$A36)^F$5+F$4*(1+C$33)/($A36-C$33)/(1+$A36)^F$5+$B$16+$B$17+$B$18)/$B$20 | D36: =(B$4/(1+$A36)^B$5+C$4/(1+$A36)^C$5+D$4/(1+$A36)^D$5+E$4/(1+$A36)^E$5+F$4/(1+$A36)^F$5+F$4*(1+D$33)/($A36-D$33)/(1+$A36)^F$5+$B$16+$B$17+$B$18)/$B$20 | E36: =(B$4/(1+$A36)^B$5+C$4/(1+$A36)^C$5+D$4/(1+$A36)^D$5+E$4/(1+$A36)^E$5+F$4/(1+$A36)^F$5+F$4*(1+E$33)/($A36-E$33)/(1+$A36)^F$5+$B$16+$B$17+$B$18)/$B$20 | F36: =(B$4/(1+$A36)^B$5+C$4/(1+$A36)^C$5+D$4/(1+$A36)^D$5+E$4/(1+$A36)^E$5+F$4/(1+$A36)^F$5+F$4*(1+F$33)/($A36-F$33)/(1+$A36)^F$5+$B$16+$B$17+$B$18)/$B$20
A37: 0.09 | B37: =(B$4/(1+$A37)^B$5+C$4/(1+$A37)^C$5+D$4/(1+$A37)^D$5+E$4/(1+$A37)^E$5+F$4/(1+$A37)^F$5+F$4*(1+B$33)/($A37-B$33)/(1+$A37)^F$5+$B$16+$B$17+$B$18)/$B$20 | C37: =(B$4/(1+$A37)^B$5+C$4/(1+$A37)^C$5+D$4/(1+$A37)^D$5+E$4/(1+$A37)^E$5+F$4/(1+$A37)^F$5+F$4*(1+C$33)/($A37-C$33)/(1+$A37)^F$5+$B$16+$B$17+$B$18)/$B$20 | D37: =(B$4/(1+$A37)^B$5+C$4/(1+$A37)^C$5+D$4/(1+$A37)^D$5+E$4/(1+$A37)^E$5+F$4/(1+$A37)^F$5+F$4*(1+D$33)/($A37-D$33)/(1+$A37)^F$5+$B$16+$B$17+$B$18)/$B$20 | E37: =(B$4/(1+$A37)^B$5+C$4/(1+$A37)^C$5+D$4/(1+$A37)^D$5+E$4/(1+$A37)^E$5+F$4/(1+$A37)^F$5+F$4*(1+E$33)/($A37-E$33)/(1+$A37)^F$5+$B$16+$B$17+$B$18)/$B$20 | F37: =(B$4/(1+$A37)^B$5+C$4/(1+$A37)^C$5+D$4/(1+$A37)^D$5+E$4/(1+$A37)^E$5+F$4/(1+$A37)^F$5+F$4*(1+F$33)/($A37-F$33)/(1+$A37)^F$5+$B$16+$B$17+$B$18)/$B$20
A38: 0.095 | B38: =(B$4/(1+$A38)^B$5+C$4/(1+$A38)^C$5+D$4/(1+$A38)^D$5+E$4/(1+$A38)^E$5+F$4/(1+$A38)^F$5+F$4*(1+B$33)/($A38-B$33)/(1+$A38)^F$5+$B$16+$B$17+$B$18)/$B$20 | C38: =(B$4/(1+$A38)^B$5+C$4/(1+$A38)^C$5+D$4/(1+$A38)^D$5+E$4/(1+$A38)^E$5+F$4/(1+$A38)^F$5+F$4*(1+C$33)/($A38-C$33)/(1+$A38)^F$5+$B$16+$B$17+$B$18)/$B$20 | D38: =(B$4/(1+$A38)^B$5+C$4/(1+$A38)^C$5+D$4/(1+$A38)^D$5+E$4/(1+$A38)^E$5+F$4/(1+$A38)^F$5+F$4*(1+D$33)/($A38-D$33)/(1+$A38)^F$5+$B$16+$B$17+$B$18)/$B$20 | E38: =(B$4/(1+$A38)^B$5+C$4/(1+$A38)^C$5+D$4/(1+$A38)^D$5+E$4/(1+$A38)^E$5+F$4/(1+$A38)^F$5+F$4*(1+E$33)/($A38-E$33)/(1+$A38)^F$5+$B$16+$B$17+$B$18)/$B$20 | F38: =(B$4/(1+$A38)^B$5+C$4/(1+$A38)^C$5+D$4/(1+$A38)^D$5+E$4/(1+$A38)^E$5+F$4/(1+$A38)^F$5+F$4*(1+F$33)/($A38-F$33)/(1+$A38)^F$5+$B$16+$B$17+$B$18)/$B$20
A39: 0.1 | B39: =(B$4/(1+$A39)^B$5+C$4/(1+$A39)^C$5+D$4/(1+$A39)^D$5+E$4/(1+$A39)^E$5+F$4/(1+$A39)^F$5+F$4*(1+B$33)/($A39-B$33)/(1+$A39)^F$5+$B$16+$B$17+$B$18)/$B$20 | C39: =(B$4/(1+$A39)^B$5+C$4/(1+$A39)^C$5+D$4/(1+$A39)^D$5+E$4/(1+$A39)^E$5+F$4/(1+$A39)^F$5+F$4*(1+C$33)/($A39-C$33)/(1+$A39)^F$5+$B$16+$B$17+$B$18)/$B$20 | D39: =(B$4/(1+$A39)^B$5+C$4/(1+$A39)^C$5+D$4/(1+$A39)^D$5+E$4/(1+$A39)^E$5+F$4/(1+$A39)^F$5+F$4*(1+D$33)/($A39-D$33)/(1+$A39)^F$5+$B$16+$B$17+$B$18)/$B$20 | E39: =(B$4/(1+$A39)^B$5+C$4/(1+$A39)^C$5+D$4/(1+$A39)^D$5+E$4/(1+$A39)^E$5+F$4/(1+$A39)^F$5+F$4*(1+E$33)/($A39-E$33)/(1+$A39)^F$5+$B$16+$B$17+$B$18)/$B$20 | F39: =(B$4/(1+$A39)^B$5+C$4/(1+$A39)^C$5+D$4/(1+$A39)^D$5+E$4/(1+$A39)^E$5+F$4/(1+$A39)^F$5+F$4*(1+F$33)/($A39-F$33)/(1+$A39)^F$5+$B$16+$B$17+$B$18)/$B$20

Sheet Comps
A1: COMPARABLE COMPANIES & CPRT HISTORY (approx. public data as of 24-Sep-2026; verify before submission)
A3: Company | B3: Ticker | C3: EV ($B) | D3: EV/EBITDA (LTM) | E3: EV/EBITDA (NTM) | F3: P/E (NTM) | G3: EBIT margin | H3: Net debt/EBITDA | I3: Comment
A4: RB Global (owns IAA) | B4: RBA | C4: 19.3 | D4: 14.8 | E4: 13 | F4: 17.9 | G4: 0.17 | H4: 1.5 | I4: Direct salvage competitor via IAA; levered; margins ~half of CPRT; StockAnalysis/Finviz
A5: OPENLANE | B5: KAR | C5: 2.9 | D5: 10 | E5: 8.5 | F5: 20 | G5: 0.1 | H5: 0.5 | I5: Digital dealer wholesale (closest ACV comp); Reuters/TickerSpark
A6: Copart - current | B6: CPRT | C6: =Inputs!$B$13/1000 | D6: =Inputs!$B$13/1882 | E6: 11.3 | F6: 17.7 | G6: 0.354 | H6: -2.3 | I6: CapIQ export; net cash
A7: Copart - 2-yr avg (CQ4-24 to CQ3-26) | B7: CPRT | E7: =Historical!$J$40 | F7: =Historical!$J$41 | G7: 0.37 | I7: CapIQ Multiples tab
A8: Copart - CQ4-2024 avg | B8: CPRT | E8: 25.8 | F8: 36.1 | G8: 0.377 | I8: Pre-derating level
A10: Peer median (RBA, KAR) | D10: =MEDIAN(D4:D5) | E10: =MEDIAN(E4:E5) | F10: =MEDIAN(F4:F5)
A12: Implied CPRT value at peer / historical multiples (on FY27E base-case figures)
A13: Basis | B13: Multiple | C13: Metric ($M / $) | D13: Implied EV | E13: Implied equity | F13: Per share | G13: vs current
A14: Peer median EV/NTM EBITDA | B14: =E10 | C14: =Scenarios!$C$77 | D14: =B14*C14 | E14: =D14+(Inputs!$B$9-Inputs!$B$116-Inputs!$B$10-Inputs!$B$11) | F14: =E14/Inputs!$B$7 | G14: =F14/Inputs!$B$6-1
A15: RBA EV/NTM EBITDA | B15: =E4 | C15: =Scenarios!$C$77 | D15: =B15*C15 | E15: =D15+(Inputs!$B$9-Inputs!$B$116-Inputs!$B$10-Inputs!$B$11) | F15: =E15/Inputs!$B$7 | G15: =F15/Inputs!$B$6-1
A16: CPRT 2-yr avg EV/NTM EBITDA | B16: =E7 | C16: =Scenarios!$C$77 | D16: =B16*C16 | E16: =D16+(Inputs!$B$9-Inputs!$B$116-Inputs!$B$10-Inputs!$B$11) | F16: =E16/Inputs!$B$7 | G16: =F16/Inputs!$B$6-1
A17: Peer median NTM P/E | B17: =F10 | C17: =Scenarios!$C$83 | F17: =B17*C17 | G17: =F17/Inputs!$B$6-1
A18: CPRT 2-yr avg NTM P/E | B18: =F7 | C18: =Scenarios!$C$83 | F18: =B18*C18 | G18: =F18/Inputs!$B$6-1
A20: Read-across: CPRT trades at a discount to RBA (IAA's parent) on P/E despite ~2x the EBIT margin, zero debt and $4.5B cash. The market is pricing structural share loss; the data (assignments +2.3% ex one customer) says cyclical.

Sheet ACV Deal
A1: ACV AUCTIONS ACQUISITION - DEAL MATH & ACCRETION (base case)
A3: Purchase price ($M) | B3: =Inputs!$B$116 | F3: Cash tender at $10.50/sh
A4: ACV CY25 revenue | B4: 760 | F4: ACV 10-K
A5: ACV CY25 adj. EBITDA | B5: 59
A6: ACV CY26E revenue (guide) | B6: =Inputs!$B$119
A7: ACV CY26E adj. EBITDA (guide mid) | B7: 75 | F7: $73-77M
A8: EV / CY25 revenue | B8: =B3/B4
A9: EV / CY25 adj. EBITDA | B9: =B3/B5
A10: EV / CY26E adj. EBITDA | B10: =B3/B7
A11: Foregone interest on cash (pre-tax, $M/yr) | B11: =B3*Inputs!$B$72 | F11: Cost of funding the deal from cash
A12: Deal amortization (pre-tax, $M/yr) | B12: =Inputs!$B$124 | F12: Non-cash
A13: Pre-tax synergies required for GAAP EPS breakeven (FY28, ex-amort.) | B13: =B11-Scenarios!D63-Scenarios!D64-Scenarios!D65 | F13: Foregone interest less ACV standalone EBIT (ex deal amort.)
A14: Base-case FY28 synergies assumed | B14: =Inputs!$C$96
A15: FY28E GAAP EPS impact of ACV (base, $) | B15: =(Scenarios!D68-B11)*(1-0.195)/Scenarios!D82 | F15: Includes deal amortization and foregone interest
A16: FY28E cash EPS impact of ACV (base, $) | B16: =(Scenarios!D68-Scenarios!D66-B11)*(1-0.195)/Scenarios!D82 | F16: Ex deal amortization
A17: Strategic logic | B17: Franchise-dealer access CPRT never cracked organically (20 yrs); 829k ACV units onto 21k acres/281 yards; buyer cross-sell; floorplan; vs. buyback at ~18x P/E = ~5.5% earnings yield
A19: Synergy sensitivity: FY28E GAAP EPS impact vs pre-tax synergies ($M)
A20: Synergies -> | B20: 0 | C20: 25 | D20: 50 | E20: 75 | F20: 100 | G20: 150
A21: FY28E GAAP EPS impact ($) | B21: =(Scenarios!$D$68-Scenarios!$D$67+B20-$B$11)*(1-0.195)/Scenarios!$D$82 | C21: =(Scenarios!$D$68-Scenarios!$D$67+C20-$B$11)*(1-0.195)/Scenarios!$D$82 | D21: =(Scenarios!$D$68-Scenarios!$D$67+D20-$B$11)*(1-0.195)/Scenarios!$D$82 | E21: =(Scenarios!$D$68-Scenarios!$D$67+E20-$B$11)*(1-0.195)/Scenarios!$D$82 | F21: =(Scenarios!$D$68-Scenarios!$D$67+F20-$B$11)*(1-0.195)/Scenarios!$D$82 | G21: =(Scenarios!$D$68-Scenarios!$D$67+G20-$B$11)*(1-0.195)/Scenarios!$D$82
